autoclean/__init__.py
autoclean/build_binary
autoclean/lmplz
autoclean/models.py
autoclean/ngram-count
autoclean/filtering/__init__.py
autoclean/filtering/api.py
autoclean/filtering/cli.py
autoclean/segmentation/__init__.py
autoclean/segmentation/api.py
autoclean/segmentation/cli.py
autoclean/segmentation/segmenters.py
autoclean/segmentation/splitters.py
autoclean-1.0.2.dist-info/METADATA
autoclean-1.0.2.dist-info/WHEEL
autoclean-1.0.2.dist-info/top_level.txt
autoclean-1.0.2.dist-info/RECORD
