Metadata-Version: 2.1
Name: autoclean
Version: 1.0.2
Summary: A library for cleaning text data
Home-page: https://github.com/JoseLlarena/autoclean
Author: Jose Llarena
Author-email: jose.llarena@gmail.com
License: MIT
Keywords: cleaning,text,unsupervised,segmentation
Platform: UNKNOWN
Classifier: Development Status :: 5 - Production/Stable
Classifier: Environment :: Other Environment
Classifier: Intended Audience :: Developers
Classifier: License :: OSI Approved :: MIT License
Classifier: Natural Language :: English
Classifier: Operating System :: OS Independent
Classifier: Programming Language :: Python :: 3
Classifier: Programming Language :: Python :: 3.8
Classifier: Programming Language :: Python :: 3.9
Classifier: Programming Language :: Python :: 3.10
Classifier: Programming Language :: Python :: 3 :: Only
Classifier: Programming Language :: Python :: Implementation :: CPython
Classifier: Topic :: Utilities
Classifier: Topic :: Software Development :: Libraries
Requires-Python: >=3.8
Requires-Dist: pypey
Requires-Dist: click
Provides-Extra: test
Requires-Dist: pytest ; extra == 'test'
